stixel/__init__.py
stixel/stixel_world_pb2.py
stixel/stixel_world_pb2.pyi
stixel/protos/__init__.py
stixel/protos/segmentation_pb2.py
stixel/protos/segmentation_pb2.pyi
stixel/utils/__init__.py
stixel/utils/detection.py
stixel/utils/packing.py
stixel/utils/transformation.py
stixel/utils/visualization.py
pyStixel_lib-0.6.5.dist-info/LICENSE
pyStixel_lib-0.6.5.dist-info/METADATA
pyStixel_lib-0.6.5.dist-info/WHEEL
pyStixel_lib-0.6.5.dist-info/top_level.txt
pyStixel_lib-0.6.5.dist-info/RECORD
