Metadata-Version: 2.1
Name: pyStixel_lib
Version: 0.6.5
Summary: The Python Stixel Library
Home-page: https://github.com/MarcelVSHNS/pyStixel-lib
Author: Marcel
Author-email: marcel.vosshans@hs-esslingen.de
License: Apache License 2.0
Requires-Python: >=3.8
License-File: LICENSE
Requires-Dist: pillow
Requires-Dist: numpy
Requires-Dist: protobuf
Requires-Dist: matplotlib
